rag_techlib-1.6.0.dist-info/licenses/LICENSE
raglib/__init__.py
raglib/cli.py
raglib/core.py
raglib/pipelines.py
raglib/plugins.py
raglib/py.typed
raglib/registry.py
raglib/schemas.py
raglib/utils.py
raglib/adapters/__init__.py
raglib/adapters/base.py
raglib/adapters/dummy_embedder.py
raglib/adapters/inmemory_vectorstore.py
raglib/architectures/__init__.py
raglib/architectures/fid.py
raglib/benchmark/__init__.py
raglib/benchmark/harness.py
raglib/benchmark/loaders.py
raglib/techniques/__init__.py
raglib/techniques/bm25.py
raglib/techniques/colbert_retriever.py
raglib/techniques/content_aware_chunker.py
raglib/techniques/crossencoder_rerank.py
raglib/techniques/dense_retriever.py
raglib/techniques/document_specific_chunker.py
raglib/techniques/dual_encoder.py
raglib/techniques/faiss_retriever.py
raglib/techniques/fixed_size_chunker.py
raglib/techniques/hyde.py
raglib/techniques/lexical_matcher.py
raglib/techniques/lexical_transformer.py
raglib/techniques/mmr.py
raglib/techniques/multi_query_retriever.py
raglib/techniques/multi_vector_retriever.py
raglib/techniques/parent_document_chunker.py
raglib/techniques/propositional_chunker.py
raglib/techniques/recursive_chunker.py
raglib/techniques/semantic_chunker.py
raglib/techniques/sentence_window_chunker.py
raglib/techniques/splade.py
raglib/techniques/tfidf.py
rag_techlib-1.6.0.dist-info/METADATA
rag_techlib-1.6.0.dist-info/WHEEL
rag_techlib-1.6.0.dist-info/entry_points.txt
rag_techlib-1.6.0.dist-info/top_level.txt
rag_techlib-1.6.0.dist-info/RECORD
