Metadata-Version: 2.4
Name: rag-techlib
Version: 1.6.0
Summary: An extensible, abstract framework for building Retrieval-Augmented Generation (RAG) systems with unlimited technique possibilities
Author-email: RAGLib Contributors <mohammad@shamlawi.com>
Maintainer-email: RAGLib Contributors <mohammad@shamlawi.com>
License-Expression: MIT
Project-URL: Homepage, https://github.com/Mohammadshamlawi/raglib
Project-URL: Repository, https://github.com/Mohammadshamlawi/raglib
Project-URL: Documentation, https://raglib.readthedocs.io
Project-URL: Bug Tracker, https://github.com/Mohammadshamlawi/raglib/issues
Project-URL: Changelog, https://github.com/Mohammadshamlawi/raglib/blob/main/CHANGELOG.md
Keywords: rag,retrieval,generation,nlp,machine-learning,ai,vector-search,embeddings
Classifier: Development Status :: 3 - Alpha
Classifier: Intended Audience :: Developers
Classifier: Intended Audience :: Science/Research
Classifier: Operating System :: OS Independent
Classifier: Programming Language :: Python :: 3
Classifier: Programming Language :: Python :: 3.9
Classifier: Programming Language :: Python :: 3.10
Classifier: Programming Language :: Python :: 3.11
Classifier: Programming Language :: Python :: 3.12
Classifier: Topic :: Scientific/Engineering :: Artificial Intelligence
Classifier: Topic :: Software Development :: Libraries :: Python Modules
Classifier: Topic :: Text Processing :: Linguistic
Classifier: Topic :: Internet :: WWW/HTTP :: Indexing/Search
Requires-Python: >=3.9
License-File: LICENSE
Requires-Dist: numpy>=1.21.0
Requires-Dist: typing-extensions>=4.0.0; python_version < "3.10"
Provides-Extra: faiss
Requires-Dist: faiss-cpu>=1.7.0; extra == "faiss"
Requires-Dist: numpy>=1.21.0; extra == "faiss"
Provides-Extra: llm
Requires-Dist: openai>=1.0.0; extra == "llm"
Requires-Dist: transformers>=4.20.0; extra == "llm"
Requires-Dist: torch>=1.12.0; extra == "llm"
Requires-Dist: tiktoken>=0.4.0; extra == "llm"
Requires-Dist: sentence-transformers>=2.2.0; extra == "llm"
Provides-Extra: docs
Requires-Dist: mkdocs>=1.5.0; extra == "docs"
Requires-Dist: mkdocs-material>=9.0.0; extra == "docs"
Requires-Dist: mkdocs-autorefs>=0.5.0; extra == "docs"
Requires-Dist: mkdocstrings[python]>=0.22.0; extra == "docs"
Requires-Dist: pymdown-extensions>=10.0.0; extra == "docs"
Requires-Dist: griffe>=0.32.0; extra == "docs"
Requires-Dist: Pillow>=9.0.0; extra == "docs"
Requires-Dist: cairosvg>=2.5.0; extra == "docs"
Provides-Extra: dev
Requires-Dist: pytest>=7.0.0; extra == "dev"
Requires-Dist: pytest-cov>=4.0.0; extra == "dev"
Requires-Dist: coverage>=7.0.0; extra == "dev"
Requires-Dist: black>=22.0.0; extra == "dev"
Requires-Dist: ruff>=0.1.0; extra == "dev"
Requires-Dist: mypy>=1.0.0; extra == "dev"
Requires-Dist: pre-commit>=3.0.0; extra == "dev"
Requires-Dist: mkdocs>=1.4.0; extra == "dev"
Requires-Dist: mkdocs-material>=9.0.0; extra == "dev"
Requires-Dist: mkdocs-autorefs>=0.4.0; extra == "dev"
Requires-Dist: mkdocstrings[python]>=0.20.0; extra == "dev"
Requires-Dist: build>=0.10.0; extra == "dev"
Requires-Dist: twine>=4.0.0; extra == "dev"
Provides-Extra: tests
Requires-Dist: pytest>=7.0.0; extra == "tests"
Requires-Dist: pytest-cov>=4.0.0; extra == "tests"
Requires-Dist: coverage>=7.0.0; extra == "tests"
Requires-Dist: pytest-mock>=3.10.0; extra == "tests"
Requires-Dist: pytest-asyncio>=0.21.0; extra == "tests"
Provides-Extra: all
Requires-Dist: rag-techlib[dev,docs,faiss,llm,tests]; extra == "all"
Dynamic: license-file
